{"image":{"0":"https:\/\/b2b-pickaboocdn.s3-ap-southeast-1.amazonaws.com\/media\/catalog\/product\/cache\/ad6eca43ef1a34982ffeb01940d91d5b\/r\/e\/realme-c12-emi-available-image.jpg","1":"https:\/\/b2b-pickaboocdn.s3-ap-southeast-1.amazonaws.com\/media\/catalog\/product\/cache\/ad6eca43ef1a34982ffeb01940d91d5b\/r\/e\/realme-7i-final-content-image.jpg","2":"https:\/\/b2b-pickaboocdn.s3-ap-southeast-1.amazonaws.com\/media\/catalog\/product\/cache\/ad6eca43ef1a34982ffeb01940d91d5b\/r\/e\/realme-7-pro-final-content-image.jpg","3":"https:\/\/b2b-pickaboocdn.s3-ap-southeast-1.amazonaws.com\/media\/catalog\/product\/cache\/ad6eca43ef1a34982ffeb01940d91d5b\/r\/e\/realme-6-878765465.jpg","4":"https:\/\/b2b-pickaboocdn.s3-ap-southeast-1.amazonaws.com\/media\/catalog\/product\/cache\/ad6eca43ef1a34982ffeb01940d91d5b\/r\/e\/realme-buds-2-wired-earphones-with-mic.jpg","5":"https:\/\/b2b-pickaboocdn.s3-ap-southeast-1.amazonaws.com\/media\/catalog\/product\/cache\/ad6eca43ef1a34982ffeb01940d91d5b\/r\/e\/realme-1.jpg","6":"https:\/\/b2b-pickaboocdn.s3-ap-southeast-1.amazonaws.com\/media\/catalog\/product\/cache\/ad6eca43ef1a34982ffeb01940d91d5b\/r\/e\/realme-buds-q-wireless-earphone.jpg","7":"https:\/\/b2b-pickaboocdn.s3-ap-southeast-1.amazonaws.com\/media\/catalog\/product\/cache\/ad6eca43ef1a34982ffeb01940d91d5b\/r\/e\/realme-band_2.jpg","8":"https:\/\/b2b-pickaboocdn.s3-ap-southeast-1.amazonaws.com\/media\/catalog\/product\/cache\/ad6eca43ef1a34982ffeb01940d91d5b\/r\/e\/realme-c17-emi.jpg","9":"https:\/\/b2b-pickaboocdn.s3-ap-southeast-1.amazonaws.com\/media\/catalog\/product\/cache\/ad6eca43ef1a34982ffeb01940d91d5b\/r\/e\/realme-c11-667gt7t.jpg","10":"https:\/\/b2b-pickaboocdn.s3-ap-southeast-1.amazonaws.com\/media\/catalog\/product\/cache\/ad6eca43ef1a34982ffeb01940d91d5b\/r\/e\/realme-6i-emi-new.jpg","11":"https:\/\/b2b-pickaboocdn.s3-ap-southeast-1.amazonaws.com\/media\/catalog\/product\/cache\/ad6eca43ef1a34982ffeb01940d91d5b\/r\/e\/realme-5i-base-image.jpg"},"name":{"0":"realme C12 3GB\/32GB","1":"realme 7i 8GB\/128GB","2":"realme 7 Pro 8GB\/128GB","3":"realme 6 8GB\/128GB","4":"realme Buds 2 Wired Earphones with Mic - Black","5":"realme Smart Watch Global Version \u2013 Black","6":"realme Buds Q Wireless Earphones - Black","7":"Realme Smart Band","8":"realme C17 6GB\/128GB","9":"realme C11 2GB\/32GB","10":"realme 6i 4GB\/128GB","11":"realme 5i 4GB\/64GB"},"price":{"0":"\u09f310,990","1":"\u09f318,990","2":"\u09f327,990","3":"\u09f322,990","4":"\u09f3770","5":"\u09f34,190","6":"\u09f31,849","7":null,"8":null,"9":null,"10":null,"11":null}}